cubicweb_bootstrap/__init__.py
cubicweb_bootstrap/__pkginfo__.py
cubicweb_bootstrap/site_cubicweb.py
cubicweb_bootstrap/uiprops.py
cubicweb_bootstrap/data/ajax-loader.gif
cubicweb_bootstrap/data/cubes.bootstrap.css
cubicweb_bootstrap/data/cubes.bootstrap.cw_compat.css
cubicweb_bootstrap/data/cubes.bootstrap.edition.js
cubicweb_bootstrap/data/cubes.bootstrap.js
cubicweb_bootstrap/data/cubicweb.form.css
cubicweb_bootstrap/data/cubicweb.tableview.css
cubicweb_bootstrap/data/go_next.png
cubicweb_bootstrap/data/go_prev.png
cubicweb_bootstrap/data/logo-cubicweb.svg
cubicweb_bootstrap/data/pen_icon.png
cubicweb_bootstrap/data/required.png
cubicweb_bootstrap/data/css/bootstrap-theme.css
cubicweb_bootstrap/data/css/bootstrap-theme.min.css
cubicweb_bootstrap/data/css/bootstrap.min.css
cubicweb_bootstrap/data/fonts/glyphicons-halflings-regular.eot
cubicweb_bootstrap/data/fonts/glyphicons-halflings-regular.svg
cubicweb_bootstrap/data/fonts/glyphicons-halflings-regular.ttf
cubicweb_bootstrap/data/fonts/glyphicons-halflings-regular.woff
cubicweb_bootstrap/data/fonts/glyphicons-halflings-regular.woff2
cubicweb_bootstrap/data/img/facet_selected.png
cubicweb_bootstrap/data/img/facet_unselected.png
cubicweb_bootstrap/data/img/table_down.png
cubicweb_bootstrap/data/img/table_sortable.png
cubicweb_bootstrap/data/img/table_up.png
cubicweb_bootstrap/data/js/bootstrap.min.js
cubicweb_bootstrap/i18n/en.po
cubicweb_bootstrap/i18n/es.po
cubicweb_bootstrap/i18n/fr.po
cubicweb_bootstrap/migration/postcreate.py
cubicweb_bootstrap/views/__init__.py
cubicweb_bootstrap/views/basecomponents.py
cubicweb_bootstrap/views/basetemplates.py
cubicweb_bootstrap/views/baseviews.py
cubicweb_bootstrap/views/boxes.py
cubicweb_bootstrap/views/component.py
cubicweb_bootstrap/views/cwproperties.py
cubicweb_bootstrap/views/debug.py
cubicweb_bootstrap/views/editforms.py
cubicweb_bootstrap/views/facets.py
cubicweb_bootstrap/views/formfields.py
cubicweb_bootstrap/views/formrenderers.py
cubicweb_bootstrap-2.1.1.dist-info/METADATA
cubicweb_bootstrap-2.1.1.dist-info/WHEEL
cubicweb_bootstrap-2.1.1.dist-info/entry_points.txt
cubicweb_bootstrap-2.1.1.dist-info/top_level.txt
cubicweb_bootstrap-2.1.1.dist-info/RECORD
